workflow_archiver/__init__.py
workflow_archiver/arg_parser.py
workflow_archiver/version.py
workflow_archiver/version.txt
workflow_archiver/workflow_archiver_error.py
workflow_archiver/workflow_packaging.py
workflow_archiver/workflow_packaging_utils.py
workflow_archiver/manifest_components/__init__.py
workflow_archiver/manifest_components/manifest.py
workflow_archiver/manifest_components/workflow.py
torch_workflow_archiver-0.2.14.dist-info/LICENSE
torch_workflow_archiver-0.2.14.dist-info/METADATA
torch_workflow_archiver-0.2.14.dist-info/WHEEL
torch_workflow_archiver-0.2.14.dist-info/entry_points.txt
torch_workflow_archiver-0.2.14.dist-info/top_level.txt
torch_workflow_archiver-0.2.14.dist-info/RECORD
