Metadata-Version: 2.1
Name: torch-workflow-archiver
Version: 0.2.14
Summary: Torch Workflow Archiver is used for creating archives of workflow designed using trained neural net models that can be consumed by TorchServe inference
Home-page: https://github.com/pytorch/serve/blob/master/workflow-archiver/
Author: PyTorch Serving team
Author-email: noreply@noreply.com
License: Apache License Version 2.0
Keywords: TorchServe Torch Workflow Archive Archiver Server Serving Deep Learning Inference AI
License-File: LICENSE
